dask_pytorch_ddp/__init__.py
dask_pytorch_ddp/data.py
dask_pytorch_ddp/dispatch.py
dask_pytorch_ddp/results.py
dask_pytorch_ddp-0.2.2.dist-info/LICENSE
dask_pytorch_ddp-0.2.2.dist-info/METADATA
dask_pytorch_ddp-0.2.2.dist-info/WHEEL
dask_pytorch_ddp-0.2.2.dist-info/top_level.txt
dask_pytorch_ddp-0.2.2.dist-info/RECORD
