Metadata-Version: 2.1
Name: dask-pytorch-ddp
Version: 0.2.2
Summary: library for setting up torch DDP on a dask cluster
Home-page: https://github.com/saturncloud/dask-pytorch-ddp
Maintainer: Saturn Cloud Developers
Maintainer-email: open-source@saturncloud.io
License: BSD 3-clause
Project-URL: Documentation, https://github.com/saturncloud/dask-pytorch-ddp
Project-URL: Source, https://github.com/saturncloud/dask-pytorch-ddp
Project-URL: Issue Tracker, https://github.com/saturncloud/dask-pytorch-ddp/issues
Keywords: saturn cloud dask pytorch torch
Platform: UNKNOWN
Classifier: Development Status :: 3 - Alpha
Classifier: License :: OSI Approved :: BSD License
Classifier: Intended Audience :: Developers
Classifier: Intended Audience :: Science/Research
Classifier: Topic :: Scientific/Engineering :: Image Processing
Classifier: Topic :: Scientific/Engineering :: Image Recognition
Classifier: Topic :: Scientific/Engineering
Classifier: Topic :: System :: Distributed Computing
Classifier: Programming Language :: Python
Classifier: Programming Language :: Python :: 3
Classifier: Programming Language :: Python :: 3.7
Requires-Python: >=3.7
Requires-Dist: dask
Requires-Dist: distributed
Requires-Dist: pillow
Requires-Dist: torch
Provides-Extra: dev
Requires-Dist: dask ; extra == 'dev'
Requires-Dist: distributed ; extra == 'dev'
Requires-Dist: pillow ; extra == 'dev'
Requires-Dist: torch ; extra == 'dev'
Requires-Dist: black ; extra == 'dev'
Requires-Dist: flake8 ; extra == 'dev'
Requires-Dist: mypy ; extra == 'dev'
Requires-Dist: pytest ; extra == 'dev'
Requires-Dist: pytest-cov ; extra == 'dev'
